pnp_mace/__init__.py
pnp_mace/agent.py
pnp_mace/equilibriumproblem.py
pnp_mace/forwardagent.py
pnp_mace/pnpadmm.py
pnp_mace/prioragent.py
pnp_mace/utils.py
pnp_mace-0.1.0.dist-info/AUTHORS.rst
pnp_mace-0.1.0.dist-info/LICENSE
pnp_mace-0.1.0.dist-info/METADATA
pnp_mace-0.1.0.dist-info/WHEEL
pnp_mace-0.1.0.dist-info/top_level.txt
pnp_mace-0.1.0.dist-info/RECORD
