Metadata-Version: 2.1
Name: pnp-mace
Version: 0.1.0
Summary: Demonstrations of the PnP algorithm and MACE framework on simple image reconstruction problems. 
Home-page: https://github.com/gbuzzard/PnP-MACE
Author: Gregery T. Buzzard
Author-email: buzzard@purdue.edu
License: BSD license
Keywords: pnp_mace
Platform: UNKNOWN
Classifier: Development Status :: 3 - Alpha
Classifier: Intended Audience :: Developers
Classifier: Intended Audience :: Education
Classifier: Intended Audience :: Science/Research
Classifier: License :: OSI Approved :: BSD License
Classifier: Natural Language :: English
Classifier: Programming Language :: Python :: 3
Classifier: Programming Language :: Python :: 3.5
Classifier: Programming Language :: Python :: 3.6
Classifier: Programming Language :: Python :: 3.7
Classifier: Programming Language :: Python :: 3.8
Requires-Python: >=3.5
Requires-Dist: numpy
Requires-Dist: matplotlib
Requires-Dist: requests
Requires-Dist: dotmap
Requires-Dist: Pillow
Requires-Dist: bm3d
